{
  "id": 76,
  "name": "The Beast",
  "version": 1,
  "factions": ["DOMINION", "LESHAVULT"],
  "health": 9,
  "energyTrack": [1, 3],
  "keywords": ["Human", "Noble", "Animal"],
  "melee": 5,
  "meleeRange": 2,
  "arcane": 0,
  "evade": 1,
  "baseSize": "30mm",
  "imageName": "beast",
  "shareCode": "AHAHG",
  "slicingDamageBuff": 2,
  "piercingDamageBuff": 1,
  "impactDamageBuff": 1,
  "dealsMagicalDamage": false,
  "allDamageMitigation": 0,
  "piercingDamageMitigation": 0,
  "impactDamageMitigation": 0,
  "slicingDamageMitigation": 0,
  "magicalDamageMitigation": 0,
  "summonsCharacterIds": [],
  "isUnselectableInTroupe": false,
  "signatureMove": {
    "name": "Bellow",
    "upgradeFor": "High Guard",
    "possibleDamageTypes": [],
    "highGuard": {
      "deal": "Null",
      "isFollowUp": false
    },
    "fallingSwing": {
      "deal": "Null",
      "isFollowUp": false
    },
    "thrust": {
      "deal": "Null",
      "isFollowUp": false
    },
    "sweepingCut": {
      "deal": "Null",
      "isFollowUp": false
    },
    "risingAttack": {
      "deal": "Null",
      "isFollowUp": false
    },
    "lowGuard": {
      "deal": "Null",
      "isFollowUp": false
    },
    "extraText": "",
    "endStepEffect": "Move the enemy 2\" directly away."
  },
  "abilities": [
    {
      "name": "Razor Claws",
      "description": "If this character deals Slicing Melee Dmg, increase the Dmg dealt by +2. If this character deals Impact or Piercing Melee Dmg, increase the Dmg dealt by +1.",
      "abilityType": "Passive",
      "oncePerTurn": false,
      "oncePerGame": false,
      "arcaneOutcomes": []
    },
    {
      "name": "Awake the Beast",
      "description": "The first time an enemy targets this character with a Melee Attack Action or an Arcane Action in a turn, this character restores 1 Wd and gains +2 energy.",
      "abilityType": "Passive",
      "oncePerTurn": false,
      "oncePerGame": false,
      "arcaneOutcomes": []
    },
    {
      "name": "Quite Terrifying",
      "description": "Whenever a non-Giant, non-Troll enemy character ends a move engaged by this model, for the first time this turn, it must discard 1 energy, if able.",
      "abilityType": "Passive",
      "oncePerTurn": false,
      "oncePerGame": false,
      "arcaneOutcomes": []
    },
    {
      "name": "Intimidate",
      "description": "Target Human or Goblin suffers -2 Arcane Stat and gains [Predictable Combatant: During a round of combat, before each player selects their combat card, you must reveal your hand to your opponent.] until end of turn.",
      "abilityType": "Active",
      "energyCost": 1,
      "range": "4\"",
      "pulse": false,
      "oncePerTurn": false,
      "oncePerGame": false,
      "arcaneOutcomes": []
    }
  ]
}
